spotifymoods/__init__.py
spotifymoods/constants.py
spotifymoods/predict.py
spotifymoods/train.py
spotifymoods-0.0.5.dist-info/LICENCE
spotifymoods-0.0.5.dist-info/METADATA
spotifymoods-0.0.5.dist-info/WHEEL
spotifymoods-0.0.5.dist-info/top_level.txt
spotifymoods-0.0.5.dist-info/RECORD
