Metadata-Version: 2.1
Name: spotifymoods
Version: 0.0.5
Summary: A simple ML model to classify Spotify tracks using audio features.
Home-page: https://github.com/ammar-oker/spotifymoods
Author: Ammar Oker
Author-email: <oker.ammar@gmail.com>
License: UNKNOWN
Keywords: spotify,machine learning,spotify moods,spotify emotions
Platform: UNKNOWN
Classifier: Development Status :: 3 - Alpha
Classifier: Intended Audience :: Education
Classifier: Programming Language :: Python :: 3
Classifier: Operating System :: MacOS :: MacOS X
Classifier: Operating System :: POSIX :: Linux
License-File: LICENCE
Requires-Dist: pandas
Requires-Dist: scikit-learn
